[
    {
        "type": "处置建议",
        "time": "2019-10-10",
        "typeBg": "blue1",
        "dec": "地震地质司",
        "cont": "倒计时覅额奇偶覅将诶及覅偶尔金佛IE哦恩金佛恩我我囧闻金佛文件"
    },
    {
        "type": "灾情上报",
        "time": "2019-10-10",
        "typeBg": "blue2",
        "dec": "科信司",
        "cont": "倒计时覅额奇偶覅将诶及覅偶尔金佛IE哦恩金佛恩我我囧闻金佛文件,"
    },
    {
        "type": "领导批示",
        "time": "2019-10-10",
        "typeBg": "red",
        "dec": "科信司",
        "cont": "倒计时覅额奇偶覅将诶及覅偶尔金佛IE哦恩金佛恩我我囧闻金佛文件"
    },
    {
        "type": "救援进展",
        "time": "2019-10-10",
        "typeBg": "green",
        "dec": "危化司",
        "cont": "倒计时覅额奇偶覅将诶及覅偶尔金佛IE哦恩金佛恩我我囧闻金佛文件"
    },
    {
        "type": "灾情评估",
        "time": "2019-10-10",
        "typeBg": "blue3",
        "dec": "危化司",
        "cont": "倒计时覅额奇偶覅将诶及覅偶尔金佛IE哦恩金佛恩我我囧闻金佛文件"
    }
]